nanpack/__init__.py
nanpack/benchmark.py
nanpack/ellipticsolvers.py
nanpack/exceptions.py
nanpack/fetchoptions.py
nanpack/grid.py
nanpack/hyperbolicsolvers.py
nanpack/limiters.py
nanpack/numericconstants.py
nanpack/parabolicsolvers.py
nanpack/postprocess.py
nanpack/preprocess.py
nanpack/scalarnavierstokes.py
nanpack/secondaryfunctions.py
nanpack/simset.py
nanpack/tridiagonal.py
nanpack/tvdfunctions.py
nanpack/backend/__init__.py
nanpack/backend/boundary.py
nanpack/backend/checkconfig.py
nanpack/backend/clustering.py
nanpack/backend/dimensionalize.py
nanpack/backend/fetchoptions.py
nanpack/backend/gridmetrics.py
nanpack/backend/initialize.py
nanpack/backend/plotmetrics.py
nanpack/input/bc.ini
nanpack/input/config-test.ini
nanpack/input/config.ini
nanpack/tests/__init__.py
nanpack/tests/context.py
nanpack/tests/test_curvgrid.py
nanpack/tests/test_nanpackinstall.py
nanpack/tests/test_run.py
nanpack/tests/test_thirdpartyinstalls.py
tests/__init__.py
tests/analyticaltest.py
tests/burgers1D.py
tests/context.py
tests/diff1D.py
tests/diff2D.py
tests/gridtest.py
tests/poissons.py
tests/tests.py
tests/wave1D.py
NAnPack-1.0.0a4.dist-info/LICENSE.md
NAnPack-1.0.0a4.dist-info/METADATA
NAnPack-1.0.0a4.dist-info/WHEEL
NAnPack-1.0.0a4.dist-info/top_level.txt
NAnPack-1.0.0a4.dist-info/RECORD
