Metadata-Version: 2.1
Name: NAnPack
Version: 1.0.0a4
Summary: A package of scientific computing tools for learning and teaching.
Home-page: https://github.com/vxsharma-14/project-NAnPack
Author: Dr. Vishal Sharma
Author-email: sharma_vishal14@hotmail.com
License: LICENSE.md
Keywords: numerical methods computational engineering computational fluid dynamics scientific computing
Platform: UNKNOWN
Classifier: Development Status :: 3 - Alpha
Classifier: Programming Language :: Python :: 3.7
Classifier: License :: OSI Approved :: MIT License
Classifier: Intended Audience :: Science/Research
Classifier: Topic :: Scientific/Engineering
Requires-Python: >=3.7
Requires-Dist: numpy
Requires-Dist: matplotlib
